[{"kkrPlayerId":"1234","kkrPlayerName":"Dinesh Karthik","kkrPlayerAddress":"nadkfb","kkrPlayerSalary":"26633"},{"kkrPlayerId":"1324","kkrPlayerName":"Visa","kkrPlayerAddress":"Thebnjkadsfb","kkrPlayerSalary":"25000"},{"kkrPlayerId":"1222","kkrPlayerName":"Shilpa","kkrPlayerAddress":"Chennai","kkrPlayerSalary":"122334"},{"kkrPlayerId":"23","kkrPlayerName":"Dhos","kkrPlayerAddress":"daf","kkrPlayerSalary":"32"},{"kkrPlayerId":"8","kkrPlayerName":"Hardik Pandya","kkrPlayerAddress":"Mumbai","kkrPlayerSalary":"30"}]